LICENSE
README.md
setup.py
app/__main__.py
app/backup.py
app/editor.py
app/googleapi.py
app/pandoc.py
app/tasks.py
app/test_pandoc.py
gtasks_md.egg-info/PKG-INFO
gtasks_md.egg-info/SOURCES.txt
gtasks_md.egg-info/dependency_links.txt
gtasks_md.egg-info/entry_points.txt
gtasks_md.egg-info/requires.txt
gtasks_md.egg-info/top_level.txt