Metadata-Version: 2.1
Name: gtasks-md
Version: 0.0.10
Summary: A tool to manage Google Tasks using a markdown document.
Home-page: https://github.com/google/gtasks-md
Author: Michal Kielbowicz
Author-email: gtasks-md@kielbowi.cz
License: Apache License 2.0
Requires-Python: >=3.11
License-File: LICENSE
